texstripper/__init__.py
texstripper/cli.py
texstripper/tex_utils/__init__.py
texstripper/tex_utils/read.py
texstripper/tex_utils/remove.py
texstripper/tex_utils/replace.py
texstripper/tex_utils/unwrap.py
texstripper-0.1.0.dist-info/METADATA
texstripper-0.1.0.dist-info/WHEEL
texstripper-0.1.0.dist-info/entry_points.txt
texstripper-0.1.0.dist-info/top_level.txt
texstripper-0.1.0.dist-info/RECORD
