Metadata-Version: 2.2
Name: texstripper
Version: 0.1.0
Summary: A tool to strip LaTeX files for Grammarly.
Home-page: https://github.com/AllenYolk/tex-stripper
Author: AllenYolk (Yifan Huang, from Peking University)
Author-email: allen.yfhuang@gmail.com
Classifier: Programming Language :: Python :: 3
Classifier: Operating System :: OS Independent
Requires-Python: >=3.6
Dynamic: author
Dynamic: author-email
Dynamic: classifier
Dynamic: description
Dynamic: description-content-type
Dynamic: home-page
Dynamic: requires-python
Dynamic: summary
